{
  "@context": "https://schema.org",
  "@type": "BreadcrumbList",
  "itemListElement": [
    {
      "@type": "ListItem",
      "position": 1,
      "name": "Home",
      "item": "https://www.clodo.dev"
    },
    {
      "@type": "ListItem",
      "position": 2,
      "name": "Case Studies",
      "item": "https://www.clodo.dev/case-studies"
    },
    {
      "@type": "ListItem",
      "position": 3,
      "name": "Companies Using Cloudflare",
      "item": "https://www.clodo.dev/saas-product-startups-cloudflare-case-studies"
    }
  ]
}
